gsf/__init__.py
gsf/decorators.py
gsf/dict.py
gsf/error.py
gsf/gsfmeta.py
gsf/job.py
gsf/server.py
gsf/service.py
gsf/task.py
gsf/utils.py
gsf/ese/__init__.py
gsf/ese/http.py
gsf/ese/job.py
gsf/ese/server.py
gsf/ese/service.py
gsf/ese/task.py
gsf/test/__init__.py
gsf/test/config.py
gsf/test/test_job.py
gsf/test/test_server.py
gsf/test/test_service.py
gsf/test/test_task.py
gsf/test/util.py
gsf-1.0.6.dist-info/DESCRIPTION.rst
gsf-1.0.6.dist-info/METADATA
gsf-1.0.6.dist-info/RECORD
gsf-1.0.6.dist-info/WHEEL
gsf-1.0.6.dist-info/metadata.json
gsf-1.0.6.dist-info/top_level.txt
