Metadata-Version: 2.0
Name: gsf
Version: 1.0.6
Summary: GSF Py
Home-page: UNKNOWN
Author: Exelis Visual Information Solutions, Inc.
Author-email: UNKNOWN
License: MIT
Keywords: gsf envi idl
Platform: UNKNOWN
